Metadata-Version: 2.1
Name: simplepydeepqlearning
Version: 1.0.3
Summary: A simple python lib to do Deep Q Learning
Home-page: https://github.com/AdrienDumontet
Author: LeLaboDuGame, https://twitch.tv/LeLaboDuGame
Author-email: 
License: Let the package like is it
Platform: UNKNOWN
